[
  {
    "id": "am86",
    "userKey": "YukakooNeko",
    "fileName": "YukakooNeko_1781163000585_am86_base The Shadow One.zip",
    "uploadedFile": "YukakooNeko_1781163000585_am86_base The Shadow One.zip",
    "zipUrl": "https://raw.githubusercontent.com/Garden354/DataApk/main/uploads/YukakooNeko_1781163000585_am86_base%20The%20Shadow%20One.zip",
    "buildType": "unknown",
    "status": "failed",
    "createdAt": 1781167232915,
    "error": "{\n  \"message\": \"Provided value 'unknown' for input 'build_type' not in the list of allowed values\",\n  \"documentation_url\": \"https://docs.github.com/rest/actions/workflows#create-a-workflow-dispatch-event\",\n  \"status\": \"422\"\n}\n"
  },
  {
    "id": "7gk2",
    "userKey": "YukakooNeko",
    "fileName": "YukakooNeko_1781165799870_7gk2_base The Shadow One.zip",
    "uploadedFile": "YukakooNeko_1781165799870_7gk2_base The Shadow One.zip",
    "zipUrl": "https://raw.githubusercontent.com/Garden354/DataApk/main/uploads/YukakooNeko_1781165799870_7gk2_base%20The%20Shadow%20One.zip",
    "buildType": "unknown",
    "status": "processing",
    "createdAt": 1781167232917
  }
]